[
    {
        "inputs": [
            {
                "internalType": "address",
                "name": "_router",
                "type": "address"
            },
            {
                "internalType": "address",
                "name": "_link",
                "type": "address"
            },
            {
                "internalType": "uint256",
                "name": "initialCreationFee",
                "type": "uint256"
            }
        ],
        "stateMutability": "nonpayable",
        "type": "constructor"
    },
    {
        "inputs": [
            {
                "internalType": "uint64",
                "name": "destinationChainSelector",
                "type": "uint64"
            }
        ],
        "name": "DestinationChainNotAllowlisted",
        "type": "error"
    },
    {
        "inputs": [
            {
                "internalType": "address",
                "name": "owner",
                "type": "address"
            },
            {
                "internalType": "address",
                "name": "target",
                "type": "address"
            },
            {
                "internalType": "uint256",
                "name": "value",
                "type": "uint256"
            }
        ],
        "name": "FailedToWithdrawEth",
        "type": "error"
    },
    {
        "inputs": [],
        "name": "InvalidReceiverAddress",
        "type": "error"
    },
    {
        "inputs": [
            {
                "internalType": "address",
                "name": "router",
                "type": "address"
            }
        ],
        "name": "InvalidRouter",
        "type": "error"
    },
    {
        "inputs": [
            {
                "internalType": "uint256",
                "name": "currentBalance",
                "type": "uint256"
            },
            {
                "internalType": "uint256",
                "name": "calculatedFees",
                "type": "uint256"
            }
        ],
        "name": "NotEnoughBalance",
        "type": "error"
    },
    {
        "inputs": [],
        "name": "NothingToWithdraw",
        "type": "error"
    },
    {
        "inputs": [
            {
                "internalType": "address",
                "name": "sender",
                "type": "address"
            }
        ],
        "name": "SenderNotAllowlisted",
        "type": "error"
    },
    {
        "inputs": [
            {
                "internalType": "uint64",
                "name": "sourceChainSelector",
                "type": "uint64"
            }
        ],
        "name": "SourceChainNotAllowlisted",
        "type": "error"
    },
    {
        "anonymous": false,
        "inputs": [
            {
                "indexed": false,
                "internalType": "uint256",
                "name": "newFee",
                "type": "uint256"
            }
        ],
        "name": "CreationFeeUpdated",
        "type": "event"
    },
    {
        "anonymous": false,
        "inputs": [
            {
                "indexed": true,
                "internalType": "bytes32",
                "name": "daoId",
                "type": "bytes32"
            },
            {
                "indexed": true,
                "internalType": "address",
                "name": "daoCreator",
                "type": "address"
            },
            {
                "indexed": false,
                "internalType": "string",
                "name": "name",
                "type": "string"
            },
            {
                "indexed": false,
                "internalType": "string",
                "name": "description",
                "type": "string"
            }
        ],
        "name": "DaoAdded",
        "type": "event"
    },
    {
        "anonymous": false,
        "inputs": [
            {
                "indexed": true,
                "internalType": "bytes32",
                "name": "messageId",
                "type": "bytes32"
            },
            {
                "indexed": true,
                "internalType": "uint64",
                "name": "sourceChainSelector",
                "type": "uint64"
            },
            {
                "indexed": false,
                "internalType": "address",
                "name": "sender",
                "type": "address"
            },
            {
                "indexed": false,
                "internalType": "string",
                "name": "text",
                "type": "string"
            }
        ],
        "name": "MessageReceived",
        "type": "event"
    },
    {
        "anonymous": false,
        "inputs": [
            {
                "indexed": true,
                "internalType": "bytes32",
                "name": "messageId",
                "type": "bytes32"
            },
            {
                "indexed": true,
                "internalType": "uint64",
                "name": "destinationChainSelector",
                "type": "uint64"
            },
            {
                "indexed": false,
                "internalType": "address",
                "name": "receiver",
                "type": "address"
            },
            {
                "indexed": false,
                "internalType": "string",
                "name": "text",
                "type": "string"
            },
            {
                "indexed": false,
                "internalType": "address",
                "name": "feeToken",
                "type": "address"
            },
            {
                "indexed": false,
                "internalType": "uint256",
                "name": "fees",
                "type": "uint256"
            }
        ],
        "name": "MessageSent",
        "type": "event"
    },
    {
        "anonymous": false,
        "inputs": [
            {
                "indexed": true,
                "internalType": "bytes32",
                "name": "daoId",
                "type": "bytes32"
            },
            {
                "indexed": false,
                "internalType": "uint256",
                "name": "newMinimum",
                "type": "uint256"
            }
        ],
        "name": "MinimumTokensUpdated",
        "type": "event"
    },
    {
        "anonymous": false,
        "inputs": [
            {
                "indexed": true,
                "internalType": "address",
                "name": "from",
                "type": "address"
            },
            {
                "indexed": true,
                "internalType": "address",
                "name": "to",
                "type": "address"
            }
        ],
        "name": "OwnershipTransferRequested",
        "type": "event"
    },
    {
        "anonymous": false,
        "inputs": [
            {
                "indexed": true,
                "internalType": "address",
                "name": "from",
                "type": "address"
            },
            {
                "indexed": true,
                "internalType": "address",
                "name": "to",
                "type": "address"
            }
        ],
        "name": "OwnershipTransferred",
        "type": "event"
    },
    {
        "anonymous": false,
        "inputs": [
            {
                "indexed": true,
                "internalType": "bytes32",
                "name": "proposalId",
                "type": "bytes32"
            },
            {
                "indexed": true,
                "internalType": "bytes32",
                "name": "daoId",
                "type": "bytes32"
            },
            {
                "indexed": false,
                "internalType": "string",
                "name": "description",
                "type": "string"
            },
            {
                "indexed": false,
                "internalType": "uint256",
                "name": "startTime",
                "type": "uint256"
            },
            {
                "indexed": false,
                "internalType": "uint256",
                "name": "endTime",
                "type": "uint256"
            },
            {
                "indexed": false,
                "internalType": "uint256",
                "name": "quorum",
                "type": "uint256"
            }
        ],
        "name": "ProposalCreated",
        "type": "event"
    },
    {
        "anonymous": false,
        "inputs": [
            {
                "indexed": true,
                "internalType": "bytes32",
                "name": "proposalId",
                "type": "bytes32"
            }
        ],
        "name": "ProposalFinalized",
        "type": "event"
    },
    {
        "anonymous": false,
        "inputs": [
            {
                "indexed": true,
                "internalType": "address",
                "name": "voter",
                "type": "address"
            },
            {
                "indexed": true,
                "internalType": "bytes32",
                "name": "proposalId",
                "type": "bytes32"
            },
            {
                "indexed": false,
                "internalType": "uint256",
                "name": "weight",
                "type": "uint256"
            }
        ],
        "name": "VoteSubmitted",
        "type": "event"
    },
    {
        "inputs": [],
        "name": "acceptOwnership",
        "outputs": [],
        "stateMutability": "nonpayable",
        "type": "function"
    },
    {
        "inputs": [
            {
                "internalType": "string",
                "name": "_name",
                "type": "string"
            },
            {
                "internalType": "string",
                "name": "_description",
                "type": "string"
            }
        ],
        "name": "addDao",
        "outputs": [
            {
                "components": [
                    {
                        "internalType": "bytes32",
                        "name": "daoId",
                        "type": "bytes32"
                    },
                    {
                        "internalType": "address",
                        "name": "daoAddress",
                        "type": "address"
                    },
                    {
                        "internalType": "string",
                        "name": "name",
                        "type": "string"
                    },
                    {
                        "internalType": "string",
                        "name": "description",
                        "type": "string"
                    }
                ],
                "internalType": "struct OmniVote.DAOInfo",
                "name": "",
                "type": "tuple"
            }
        ],
        "stateMutability": "payable",
        "type": "function"
    },
    {
        "inputs": [
            {
                "internalType": "uint64",
                "name": "_destinationChainSelector",
                "type": "uint64"
            },
            {
                "internalType": "bool",
                "name": "allowed",
                "type": "bool"
            }
        ],
        "name": "allowlistDestinationChain",
        "outputs": [],
        "stateMutability": "nonpayable",
        "type": "function"
    },
    {
        "inputs": [
            {
                "internalType": "address",
                "name": "_sender",
                "type": "address"
            },
            {
                "internalType": "bool",
                "name": "allowed",
                "type": "bool"
            }
        ],
        "name": "allowlistSender",
        "outputs": [],
        "stateMutability": "nonpayable",
        "type": "function"
    },
    {
        "inputs": [
            {
                "internalType": "uint64",
                "name": "_sourceChainSelector",
                "type": "uint64"
            },
            {
                "internalType": "bool",
                "name": "allowed",
                "type": "bool"
            }
        ],
        "name": "allowlistSourceChain",
        "outputs": [],
        "stateMutability": "nonpayable",
        "type": "function"
    },
    {
        "inputs": [
            {
                "internalType": "uint64",
                "name": "",
                "type": "uint64"
            }
        ],
        "name": "allowlistedDestinationChains",
        "outputs": [
            {
                "internalType": "bool",
                "name": "",
                "type": "bool"
            }
        ],
        "stateMutability": "view",
        "type": "function"
    },
    {
        "inputs": [
            {
                "internalType": "address",
                "name": "",
                "type": "address"
            }
        ],
        "name": "allowlistedSenders",
        "outputs": [
            {
                "internalType": "bool",
                "name": "",
                "type": "bool"
            }
        ],
        "stateMutability": "view",
        "type": "function"
    },
    {
        "inputs": [
            {
                "internalType": "uint64",
                "name": "",
                "type": "uint64"
            }
        ],
        "name": "allowlistedSourceChains",
        "outputs": [
            {
                "internalType": "bool",
                "name": "",
                "type": "bool"
            }
        ],
        "stateMutability": "view",
        "type": "function"
    },
    {
        "inputs": [
            {
                "components": [
                    {
                        "internalType": "bytes32",
                        "name": "messageId",
                        "type": "bytes32"
                    },
                    {
                        "internalType": "uint64",
                        "name": "sourceChainSelector",
                        "type": "uint64"
                    },
                    {
                        "internalType": "bytes",
                        "name": "sender",
                        "type": "bytes"
                    },
                    {
                        "internalType": "bytes",
                        "name": "data",
                        "type": "bytes"
                    },
                    {
                        "components": [
                            {
                                "internalType": "address",
                                "name": "token",
                                "type": "address"
                            },
                            {
                                "internalType": "uint256",
                                "name": "amount",
                                "type": "uint256"
                            }
                        ],
                        "internalType": "struct Client.EVMTokenAmount[]",
                        "name": "destTokenAmounts",
                        "type": "tuple[]"
                    }
                ],
                "internalType": "struct Client.Any2EVMMessage",
                "name": "message",
                "type": "tuple"
            }
        ],
        "name": "ccipReceive",
        "outputs": [],
        "stateMutability": "nonpayable",
        "type": "function"
    },
    {
        "inputs": [
            {
                "internalType": "bytes32",
                "name": "_daoId",
                "type": "bytes32"
            },
            {
                "internalType": "string",
                "name": "_description",
                "type": "string"
            },
            {
                "internalType": "uint256",
                "name": "_startTime",
                "type": "uint256"
            },
            {
                "internalType": "uint256",
                "name": "_endTime",
                "type": "uint256"
            },
            {
                "internalType": "uint256",
                "name": "_quorum",
                "type": "uint256"
            }
        ],
        "name": "createProposal",
        "outputs": [
            {
                "internalType": "bytes32",
                "name": "",
                "type": "bytes32"
            }
        ],
        "stateMutability": "nonpayable",
        "type": "function"
    },
    {
        "inputs": [],
        "name": "creationFee",
        "outputs": [
            {
                "internalType": "uint256",
                "name": "",
                "type": "uint256"
            }
        ],
        "stateMutability": "view",
        "type": "function"
    },
    {
        "inputs": [
            {
                "internalType": "uint256",
                "name": "",
                "type": "uint256"
            }
        ],
        "name": "daoIds",
        "outputs": [
            {
                "internalType": "bytes32",
                "name": "",
                "type": "bytes32"
            }
        ],
        "stateMutability": "view",
        "type": "function"
    },
    {
        "inputs": [
            {
                "internalType": "bytes32",
                "name": "",
                "type": "bytes32"
            }
        ],
        "name": "daos",
        "outputs": [
            {
                "internalType": "bytes32",
                "name": "daoId",
                "type": "bytes32"
            },
            {
                "internalType": "address",
                "name": "daoAddress",
                "type": "address"
            },
            {
                "internalType": "string",
                "name": "name",
                "type": "string"
            },
            {
                "internalType": "string",
                "name": "description",
                "type": "string"
            }
        ],
        "stateMutability": "view",
        "type": "function"
    },
    {
        "inputs": [
            {
                "internalType": "bytes32",
                "name": "_proposalId",
                "type": "bytes32"
            }
        ],
        "name": "finalizeProposal",
        "outputs": [],
        "stateMutability": "nonpayable",
        "type": "function"
    },
    {
        "inputs": [],
        "name": "getAllDaos",
        "outputs": [
            {
                "components": [
                    {
                        "internalType": "bytes32",
                        "name": "daoId",
                        "type": "bytes32"
                    },
                    {
                        "internalType": "address",
                        "name": "daoAddress",
                        "type": "address"
                    },
                    {
                        "internalType": "string",
                        "name": "name",
                        "type": "string"
                    },
                    {
                        "internalType": "string",
                        "name": "description",
                        "type": "string"
                    }
                ],
                "internalType": "struct OmniVote.DAOInfo[]",
                "name": "",
                "type": "tuple[]"
            }
        ],
        "stateMutability": "view",
        "type": "function"
    },
    {
        "inputs": [],
        "name": "getAllProposals",
        "outputs": [
            {
                "components": [
                    {
                        "internalType": "bytes32",
                        "name": "proposalId",
                        "type": "bytes32"
                    },
                    {
                        "internalType": "string",
                        "name": "description",
                        "type": "string"
                    },
                    {
                        "internalType": "uint256",
                        "name": "startTime",
                        "type": "uint256"
                    },
                    {
                        "internalType": "uint256",
                        "name": "endTime",
                        "type": "uint256"
                    },
                    {
                        "internalType": "uint256",
                        "name": "quorum",
                        "type": "uint256"
                    },
                    {
                        "internalType": "uint256",
                        "name": "totalVotes",
                        "type": "uint256"
                    }
                ],
                "internalType": "struct OmniVote.Proposal[]",
                "name": "",
                "type": "tuple[]"
            }
        ],
        "stateMutability": "view",
        "type": "function"
    },
    {
        "inputs": [],
        "name": "getLastReceivedMessageDetails",
        "outputs": [
            {
                "internalType": "bytes32",
                "name": "messageId",
                "type": "bytes32"
            },
            {
                "internalType": "string",
                "name": "text",
                "type": "string"
            }
        ],
        "stateMutability": "view",
        "type": "function"
    },
    {
        "inputs": [
            {
                "internalType": "bytes32",
                "name": "_proposalId",
                "type": "bytes32"
            }
        ],
        "name": "getProposalDetails",
        "outputs": [
            {
                "internalType": "string",
                "name": "description",
                "type": "string"
            },
            {
                "internalType": "uint256",
                "name": "startTime",
                "type": "uint256"
            },
            {
                "internalType": "uint256",
                "name": "endTime",
                "type": "uint256"
            },
            {
                "internalType": "uint256",
                "name": "quorum",
                "type": "uint256"
            },
            {
                "internalType": "uint256",
                "name": "totalVotes",
                "type": "uint256"
            }
        ],
        "stateMutability": "view",
        "type": "function"
    },
    {
        "inputs": [],
        "name": "getRouter",
        "outputs": [
            {
                "internalType": "address",
                "name": "",
                "type": "address"
            }
        ],
        "stateMutability": "view",
        "type": "function"
    },
    {
        "inputs": [],
        "name": "owner",
        "outputs": [
            {
                "internalType": "address",
                "name": "",
                "type": "address"
            }
        ],
        "stateMutability": "view",
        "type": "function"
    },
    {
        "inputs": [
            {
                "internalType": "uint256",
                "name": "",
                "type": "uint256"
            }
        ],
        "name": "proposalIds",
        "outputs": [
            {
                "internalType": "bytes32",
                "name": "",
                "type": "bytes32"
            }
        ],
        "stateMutability": "view",
        "type": "function"
    },
    {
        "inputs": [
            {
                "internalType": "bytes32",
                "name": "",
                "type": "bytes32"
            }
        ],
        "name": "proposals",
        "outputs": [
            {
                "internalType": "bytes32",
                "name": "proposalId",
                "type": "bytes32"
            },
            {
                "internalType": "string",
                "name": "description",
                "type": "string"
            },
            {
                "internalType": "uint256",
                "name": "startTime",
                "type": "uint256"
            },
            {
                "internalType": "uint256",
                "name": "endTime",
                "type": "uint256"
            },
            {
                "internalType": "uint256",
                "name": "quorum",
                "type": "uint256"
            },
            {
                "internalType": "uint256",
                "name": "totalVotes",
                "type": "uint256"
            }
        ],
        "stateMutability": "view",
        "type": "function"
    },
    {
        "inputs": [
            {
                "internalType": "uint256",
                "name": "newFee",
                "type": "uint256"
            }
        ],
        "name": "setCreationFee",
        "outputs": [],
        "stateMutability": "nonpayable",
        "type": "function"
    },
    {
        "inputs": [
            {
                "internalType": "bytes32",
                "name": "_proposalId",
                "type": "bytes32"
            },
            {
                "internalType": "uint256",
                "name": "_weight",
                "type": "uint256"
            }
        ],
        "name": "submitVote",
        "outputs": [],
        "stateMutability": "nonpayable",
        "type": "function"
    },
    {
        "inputs": [
            {
                "internalType": "uint64",
                "name": "_destinationChainSelector",
                "type": "uint64"
            },
            {
                "internalType": "address",
                "name": "_receiver",
                "type": "address"
            },
            {
                "internalType": "string",
                "name": "_proposalIdText",
                "type": "string"
            }
        ],
        "name": "submitVoteCrossChain",
        "outputs": [
            {
                "internalType": "bytes32",
                "name": "messageId",
                "type": "bytes32"
            }
        ],
        "stateMutability": "nonpayable",
        "type": "function"
    },
    {
        "inputs": [
            {
                "internalType": "bytes4",
                "name": "interfaceId",
                "type": "bytes4"
            }
        ],
        "name": "supportsInterface",
        "outputs": [
            {
                "internalType": "bool",
                "name": "",
                "type": "bool"
            }
        ],
        "stateMutability": "pure",
        "type": "function"
    },
    {
        "inputs": [
            {
                "internalType": "address",
                "name": "to",
                "type": "address"
            }
        ],
        "name": "transferOwnership",
        "outputs": [],
        "stateMutability": "nonpayable",
        "type": "function"
    },
    {
        "inputs": [
            {
                "internalType": "address",
                "name": "",
                "type": "address"
            }
        ],
        "name": "whitelistedUsers",
        "outputs": [
            {
                "internalType": "bool",
                "name": "",
                "type": "bool"
            }
        ],
        "stateMutability": "view",
        "type": "function"
    },
    {
        "inputs": [
            {
                "internalType": "address",
                "name": "_beneficiary",
                "type": "address"
            }
        ],
        "name": "withdraw",
        "outputs": [],
        "stateMutability": "nonpayable",
        "type": "function"
    },
    {
        "inputs": [
            {
                "internalType": "address",
                "name": "_beneficiary",
                "type": "address"
            },
            {
                "internalType": "address",
                "name": "_token",
                "type": "address"
            }
        ],
        "name": "withdrawToken",
        "outputs": [],
        "stateMutability": "nonpayable",
        "type": "function"
    },
    {
        "stateMutability": "payable",
        "type": "receive"
    }
]
